{"cluster": 20, "subcluster": 59, "abstract_phrases": [{"text": "sars-cov-2 assay", "rank": 0.11}, {"text": "fusion assay", "rank": 0.105}, {"text": "assay", "rank": 0.104}, {"text": "realtime sars-cov-2 assay", "rank": 0.104}, {"text": "assay agreement", "rank": 0.104}], "title_phrases": [{"text": "nucleic acid amplification tests", "rank": 0.159}, {"text": "laboratory-developed test", "rank": 0.151}, {"text": "molecular tests", "rank": 0.14}, {"text": "sars-cov-2 detection", "rank": 0.119}, {"text": "diagnostic assays", "rank": 0.119}], "title_abstract_phrases": [{"text": "sars-cov-2 assay", "rank": 0.109}, {"text": "realtime sars-cov-2 assay", "rank": 0.103}, {"text": "assay", "rank": 0.103}, {"text": "fusion assay", "rank": 0.103}, {"text": "assay agreement", "rank": 0.102}]}