{"cluster": 20, "subcluster": 27, "abstract_phrases": [{"text": "antibody response", "rank": 0.094}, {"text": "serological antibody responses", "rank": 0.089}, {"text": "neutralizing antibodies", "rank": 0.088}, {"text": "antibodies", "rank": 0.085}, {"text": "serum antibodies", "rank": 0.084}], "title_phrases": [{"text": "functional antibody responses", "rank": 0.165}, {"text": "convergent antibody responses", "rank": 0.162}, {"text": "sars-cov-2 spikecross-reactive antibody", "rank": 0.146}, {"text": "humoral responses", "rank": 0.135}, {"text": "responses", "rank": 0.134}], "title_abstract_phrases": [{"text": "antibody response", "rank": 0.1}, {"text": "cross-reactive antibody response", "rank": 0.095}, {"text": "functional antibody responses", "rank": 0.095}, {"text": "serological antibody responses", "rank": 0.095}, {"text": "convergent antibody responses", "rank": 0.093}]}