{"cluster": 20, "subcluster": 80, "abstract_phrases": [{"text": "serum samples", "rank": 0.081}, {"text": "serum antibody", "rank": 0.079}, {"text": "serological assays", "rank": 0.074}, {"text": "gold immunochromatographic assay", "rank": 0.072}, {"text": "viral serological test", "rank": 0.072}], "title_phrases": [{"text": "sars-cov-2 serological tools", "rank": 0.167}, {"text": "serological assay", "rank": 0.158}, {"text": "analytical performance", "rank": 0.146}, {"text": "clinical practicedynamic profile", "rank": 0.142}, {"text": "sars-cov-2 igm/igg", "rank": 0.141}], "title_abstract_phrases": [{"text": "serological assays", "rank": 0.08}, {"text": "serum antibody", "rank": 0.079}, {"text": "serum samples", "rank": 0.078}, {"text": "gold immunochromatographic assay", "rank": 0.075}, {"text": "viral serological test", "rank": 0.074}]}