{"cluster": 23, "subcluster": 327, "abstract_phrases": [{"text": "covid-19 cases", "rank": 0.101}, {"text": "new covid-19 cases", "rank": 0.1}, {"text": "reported covid-19 cases", "rank": 0.097}, {"text": "higher monthly covid-19 cases", "rank": 0.093}, {"text": "covid-19 infections", "rank": 0.09}], "title_phrases": [{"text": "covid-19 pandemic", "rank": 0.164}, {"text": "covid-19 incidence", "rank": 0.161}, {"text": "covid-19", "rank": 0.157}, {"text": "sir", "rank": 0.11}, {"text": "statistical modeling", "rank": 0.105}], "title_abstract_phrases": [{"text": "covid-19 cases", "rank": 0.105}, {"text": "new covid-19 cases", "rank": 0.103}, {"text": "reported covid-19 cases", "rank": 0.1}, {"text": "higher monthly covid-19 cases", "rank": 0.096}, {"text": "covid-19 infections", "rank": 0.093}]}