{"cluster": 23, "subcluster": 133, "abstract_phrases": [{"text": "local case data", "rank": 0.071}, {"text": "infection rate", "rank": 0.069}, {"text": "covid-19 infection", "rank": 0.069}, {"text": "local infection", "rank": 0.068}, {"text": "case data", "rank": 0.063}], "title_phrases": [{"text": "simplified arithmetic tools", "rank": 0.12}, {"text": "lessons", "rank": 0.115}, {"text": "national unity", "rank": 0.11}, {"text": "global solidarity", "rank": 0.11}, {"text": "general public", "rank": 0.109}], "title_abstract_phrases": [{"text": "covid-19 infection", "rank": 0.069}, {"text": "local case data", "rank": 0.069}, {"text": "infection rate", "rank": 0.067}, {"text": "local infection", "rank": 0.066}, {"text": "case data", "rank": 0.061}]}