{"cluster": 23, "subcluster": 279, "abstract_phrases": [{"text": "covid-19 transmission model", "rank": 0.077}, {"text": "covid-19 disease", "rank": 0.07}, {"text": "reproduction number", "rank": 0.067}, {"text": "media impact", "rank": 0.066}, {"text": "media data", "rank": 0.066}], "title_phrases": [{"text": "covid-19 pandemicimpact", "rank": 0.146}, {"text": "covid-19", "rank": 0.131}, {"text": "early spread", "rank": 0.127}, {"text": "media reports", "rank": 0.124}, {"text": "quarantine measures", "rank": 0.122}], "title_abstract_phrases": [{"text": "covid-19 transmission model", "rank": 0.08}, {"text": "covid-19 disease", "rank": 0.073}, {"text": "media impact", "rank": 0.068}, {"text": "media data", "rank": 0.066}, {"text": "reproduction number", "rank": 0.065}]}