{"cluster": 23, "subcluster": 149, "abstract_phrases": [{"text": "public health interventions", "rank": 0.091}, {"text": "public health intervention strategies", "rank": 0.088}, {"text": "multiple public health intervention problems", "rank": 0.085}, {"text": "public health", "rank": 0.083}, {"text": "public health benefits", "rank": 0.079}], "title_phrases": [{"text": "bayesian optimizationrecurrent neural reinforcement learning", "rank": 0.118}, {"text": "reinforcement learninggenetic programming visitation scheduling solution", "rank": 0.115}, {"text": "neural reinforcement learning", "rank": 0.113}, {"text": "reinforcement learning", "rank": 0.112}, {"text": "epidemic control", "rank": 0.107}], "title_abstract_phrases": [{"text": "public health interventions", "rank": 0.09}, {"text": "public health intervention strategies", "rank": 0.088}, {"text": "multiple public health intervention problems", "rank": 0.084}, {"text": "public health benefits", "rank": 0.078}, {"text": "public health planning", "rank": 0.078}]}