{"cluster": 23, "subcluster": 296, "abstract_phrases": [{"text": "reproduction number", "rank": 0.094}, {"text": "basic reproduction number", "rank": 0.093}, {"text": "time dependent reproduction numbers", "rank": 0.084}, {"text": "net reproductive number values", "rank": 0.083}, {"text": "numbers", "rank": 0.08}], "title_phrases": [{"text": "basic reproduction number", "rank": 0.174}, {"text": "covid-19 epidemic size", "rank": 0.145}, {"text": "time-varying reproduction", "rank": 0.139}, {"text": "covid-19 outbreak", "rank": 0.139}, {"text": "reproduction", "rank": 0.131}], "title_abstract_phrases": [{"text": "reproduction number", "rank": 0.099}, {"text": "basic reproduction number", "rank": 0.098}, {"text": "time-varying reproduction number estimation", "rank": 0.09}, {"text": "time dependent reproduction numbers", "rank": 0.088}, {"text": "net reproductive number values", "rank": 0.084}]}