{"cluster": 23, "subcluster": 105, "abstract_phrases": [{"text": "fractional system", "rank": 0.092}, {"text": "caputo model", "rank": 0.091}, {"text": "new mathematical model", "rank": 0.09}, {"text": "fuzzy fractional differential systems", "rank": 0.09}, {"text": "mathematical model", "rank": 0.089}], "title_phrases": [{"text": "fractional differential equation model", "rank": 0.143}, {"text": "non-singular fractional derivativestability analysis", "rank": 0.128}, {"text": "covid-19 mathematical model", "rank": 0.124}, {"text": "fractional derivatives", "rank": 0.124}, {"text": "fractional chebyshev polynomialsa", "rank": 0.122}], "title_abstract_phrases": [{"text": "fractional differential equation model", "rank": 0.109}, {"text": "fractional system", "rank": 0.093}, {"text": "caputo model", "rank": 0.093}, {"text": "mathematical model", "rank": 0.093}, {"text": "new mathematical model", "rank": 0.092}]}