{"cluster": 23, "subcluster": 130, "abstract_phrases": [{"text": "physical distancing measures", "rank": 0.089}, {"text": "physical contact", "rank": 0.087}, {"text": "unprecedented physical distancing policies", "rank": 0.081}, {"text": "physical distancing", "rank": 0.081}, {"text": "measured contact patterns", "rank": 0.076}], "title_phrases": [{"text": "physical distance measures", "rank": 0.146}, {"text": "fighting communicable virus", "rank": 0.135}, {"text": "physical distance", "rank": 0.129}, {"text": "communicable virus", "rank": 0.113}, {"text": "impact", "rank": 0.112}], "title_abstract_phrases": [{"text": "physical distancing measures", "rank": 0.091}, {"text": "physical contact", "rank": 0.089}, {"text": "physical distancing", "rank": 0.081}, {"text": "unprecedented physical distancing policies", "rank": 0.081}, {"text": "physical distance measures", "rank": 0.08}]}