{"cluster": 25, "subcluster": 16, "abstract_phrases": [{"text": "pregnant women", "rank": 0.096}, {"text": "women", "rank": 0.091}, {"text": "most women", "rank": 0.088}, {"text": "sars-cov-2 infection", "rank": 0.072}, {"text": "sars-cov-2 positive", "rank": 0.068}], "title_phrases": [{"text": "medical records chen h", "rank": 0.117}, {"text": "new york city medical centers", "rank": 0.113}, {"text": "large managed care organization", "rank": 0.108}, {"text": "acute respiratory syndrome", "rank": 0.106}, {"text": "national population-based cohort", "rank": 0.102}], "title_abstract_phrases": [{"text": "pregnant women", "rank": 0.093}, {"text": "women", "rank": 0.088}, {"text": "most women", "rank": 0.085}, {"text": "covid-19 infection", "rank": 0.076}, {"text": "sars-cov-2 infection", "rank": 0.071}]}