{"cluster": 2, "subcluster": 6, "abstract_phrases": [{"text": "agile teams", "rank": 0.111}, {"text": "multiple agile teams", "rank": 0.104}, {"text": "product development teams", "rank": 0.1}, {"text": "cross-functional product development teams", "rank": 0.096}, {"text": "product teams", "rank": 0.095}], "title_phrases": [{"text": "agile teamlarge-scale agile transformation", "rank": 0.16}, {"text": "agile software development", "rank": 0.149}, {"text": "agile project", "rank": 0.132}, {"text": "agile leader", "rank": 0.127}, {"text": "activity theory perspectiveagile software development practices", "rank": 0.116}], "title_abstract_phrases": [{"text": "agile teams", "rank": 0.107}, {"text": "multiple agile teams", "rank": 0.1}, {"text": "product development teams", "rank": 0.096}, {"text": "cross-functional product development teams", "rank": 0.092}, {"text": "product teams", "rank": 0.09}]}