{"cluster": 34, "subcluster": 15, "abstract_phrases": [{"text": "used face masks", "rank": 0.102}, {"text": "face masks", "rank": 0.099}, {"text": "mask particle", "rank": 0.097}, {"text": "masks", "rank": 0.096}, {"text": "cloth masks", "rank": 0.095}], "title_phrases": [{"text": "respiratory masks", "rank": 0.104}, {"text": "homemade respiratory masks", "rank": 0.098}, {"text": "respiratory jetsface mask designs", "rank": 0.098}, {"text": "face masks", "rank": 0.094}, {"text": "respiratory droplet transmission", "rank": 0.091}], "title_abstract_phrases": [{"text": "face masks", "rank": 0.098}, {"text": "mask particle", "rank": 0.095}, {"text": "respiratory masks", "rank": 0.094}, {"text": "cloth masks", "rank": 0.093}, {"text": "face mask designs", "rank": 0.093}]}