{"cluster": 43, "subcluster": 20, "abstract_phrases": [{"text": "severe covid\u201019", "rank": 0.079}, {"text": "coronavirus disease", "rank": 0.076}, {"text": "cytokine storm syndrome", "rank": 0.076}, {"text": "cytokine release syndrome", "rank": 0.073}, {"text": "patient", "rank": 0.072}], "title_phrases": [{"text": "patients", "rank": 0.132}, {"text": "covid-19 infection", "rank": 0.115}, {"text": "subcutaneous tocilizumab", "rank": 0.108}, {"text": "covid-19", "rank": 0.102}, {"text": "sars\u2010cov\u20102 infection", "rank": 0.101}], "title_abstract_phrases": [{"text": "patient", "rank": 0.084}, {"text": "covid-19 infections", "rank": 0.073}, {"text": "covid\u201019 pneumonia", "rank": 0.07}, {"text": "cytokine storm syndrome", "rank": 0.069}, {"text": "coronavirus disease", "rank": 0.069}]}