{"cluster": 48, "subcluster": 3, "abstract_phrases": [{"text": "viral nucleic acid tests", "rank": 0.135}, {"text": "nucleic acid tests", "rank": 0.132}, {"text": "viral nucleic acid", "rank": 0.131}, {"text": "covid-19 nucleic acid test", "rank": 0.13}, {"text": "early nucleic acid tests", "rank": 0.128}], "title_phrases": [{"text": "viral nucleic acid", "rank": 0.191}, {"text": "covid-19 nucleic acid tests", "rank": 0.187}, {"text": "viral nucleic acid tests", "rank": 0.186}, {"text": "patients", "rank": 0.125}, {"text": "covid-19[follow-up testing", "rank": 0.114}], "title_abstract_phrases": [{"text": "viral nucleic acid tests", "rank": 0.141}, {"text": "nucleic acid tests", "rank": 0.137}, {"text": "viral nucleic acid", "rank": 0.137}, {"text": "covid-19 nucleic acid tests", "rank": 0.135}, {"text": "early nucleic acid tests", "rank": 0.132}]}