{"cluster": 50, "subcluster": 47, "abstract_phrases": [{"text": "coronavirus disease", "rank": 0.082}, {"text": "nasopharyngeal swab/saliva sample", "rank": 0.076}, {"text": "nasopharyngeal swab samples", "rank": 0.076}, {"text": "covid-19 infection", "rank": 0.075}, {"text": "nasopharyngeal swabs", "rank": 0.075}], "title_phrases": [{"text": "coronavirus disease", "rank": 0.134}, {"text": "acute respiratory syndrome", "rank": 0.126}, {"text": "coronavirus", "rank": 0.12}, {"text": "nasopharyngeal swabs", "rank": 0.111}, {"text": "sars\u2010cov\u20102 detection", "rank": 0.103}], "title_abstract_phrases": [{"text": "coronavirus disease", "rank": 0.095}, {"text": "detectable severe acute respiratory syndrome coronavirus", "rank": 0.095}, {"text": "coronavirus", "rank": 0.085}, {"text": "nasopharyngeal swabs", "rank": 0.079}, {"text": "nasopharyngeal swab samples", "rank": 0.078}]}