{"cluster": 50, "subcluster": 34, "abstract_phrases": [{"text": "covid-19 patients", "rank": 0.085}, {"text": "covid-19", "rank": 0.083}, {"text": "test multiple covid-19", "rank": 0.083}, {"text": "covid-19 candidate therapeutics", "rank": 0.082}, {"text": "multiple covid-19 interventions", "rank": 0.081}], "title_phrases": [{"text": "covid-19 candidate therapeutics", "rank": 0.162}, {"text": "covid-19 outbreak", "rank": 0.153}, {"text": "covid-19", "rank": 0.15}, {"text": "discovery clinical trial", "rank": 0.125}, {"text": "adaptively randomized trials", "rank": 0.113}], "title_abstract_phrases": [{"text": "covid-19 pandemic", "rank": 0.099}, {"text": "covid-19 trials", "rank": 0.099}, {"text": "covid-19 outbreak", "rank": 0.098}, {"text": "covid-19 candidate therapeutics", "rank": 0.094}, {"text": "covid-19", "rank": 0.093}]}