{"cluster": 55, "subcluster": 64, "abstract_phrases": [{"text": "public health", "rank": 0.075}, {"text": "public health emergency", "rank": 0.072}, {"text": "existing health inequities", "rank": 0.071}, {"text": "health systems", "rank": 0.071}, {"text": "health", "rank": 0.069}], "title_phrases": [{"text": "health inequity", "rank": 0.089}, {"text": "health equity", "rank": 0.086}, {"text": "covid-19 transmission", "rank": 0.086}, {"text": "policy advocacy", "rank": 0.086}, {"text": "reduce", "rank": 0.082}], "title_abstract_phrases": [{"text": "public health", "rank": 0.072}, {"text": "public health emergency", "rank": 0.068}, {"text": "existing health inequities", "rank": 0.068}, {"text": "health systems", "rank": 0.068}, {"text": "social policy", "rank": 0.067}]}