{"cluster": 55, "subcluster": 21, "abstract_phrases": [{"text": "crisis management", "rank": 0.076}, {"text": "crisis management strategies", "rank": 0.075}, {"text": "disaster risk", "rank": 0.073}, {"text": "crisis management process", "rank": 0.073}, {"text": "islamic crisis management model", "rank": 0.071}], "title_phrases": [{"text": "covid\u201019 pandemic crisis", "rank": 0.114}, {"text": "saudi arabiapersonnel training course", "rank": 0.111}, {"text": "a policy analysispublic perception", "rank": 0.107}, {"text": "covid-19 crisis", "rank": 0.099}, {"text": "response", "rank": 0.098}], "title_abstract_phrases": [{"text": "crisis management", "rank": 0.076}, {"text": "crisis management strategies", "rank": 0.076}, {"text": "disaster management", "rank": 0.076}, {"text": "crisis management process", "rank": 0.073}, {"text": "islamic crisis management model", "rank": 0.073}]}