{"cluster": 55, "subcluster": 61, "abstract_phrases": [{"text": "jail system", "rank": 0.065}, {"text": "u.s. correctional system", "rank": 0.063}, {"text": "correctional systems", "rank": 0.061}, {"text": "correctional facilities", "rank": 0.059}, {"text": "community infections", "rank": 0.056}], "title_phrases": [{"text": "u.s. correctional system", "rank": 0.121}, {"text": "u.s. immigrant detention centers", "rank": 0.115}, {"text": "progressive criminal justice reform", "rank": 0.104}, {"text": "covid-19 pandemic lessons", "rank": 0.103}, {"text": "u.s.", "rank": 0.096}], "title_abstract_phrases": [{"text": "u.s. correctional system", "rank": 0.065}, {"text": "jail system", "rank": 0.062}, {"text": "correctional systems", "rank": 0.058}, {"text": "decarcerationthe covid-19 pandemic", "rank": 0.057}, {"text": "disease covid-19", "rank": 0.057}]}