{"cluster": 69, "subcluster": 58, "abstract_phrases": [{"text": "cancer care", "rank": 0.093}, {"text": "cancer care providers", "rank": 0.088}, {"text": "delay cancer", "rank": 0.081}, {"text": "anal cancers", "rank": 0.079}, {"text": "early anal cancers", "rank": 0.077}], "title_phrases": [{"text": "covid-19 pandemic", "rank": 0.145}, {"text": "covid-19 pandemic-an expert consensus", "rank": 0.143}, {"text": "covid-19", "rank": 0.134}, {"text": "ocular oncology practice guidelines", "rank": 0.125}, {"text": "cancer surgery triage guidelines", "rank": 0.124}], "title_abstract_phrases": [{"text": "cancer care", "rank": 0.093}, {"text": "cancer care providers", "rank": 0.088}, {"text": "delay cancer", "rank": 0.081}, {"text": "anal cancers", "rank": 0.078}, {"text": "cancer", "rank": 0.077}]}