{"cluster": 6, "subcluster": 0, "abstract_phrases": [{"text": "laser power calibration standards", "rank": 0.085}, {"text": "laser power calibration", "rank": 0.084}, {"text": "laser power sensor calibration", "rank": 0.083}, {"text": "improved laser power sensor calibration accuracy", "rank": 0.083}, {"text": "calibration accuracy", "rank": 0.071}], "title_phrases": [{"text": "millimeter-wave chirped pulse instrumentationa calibration disk", "rank": 0.116}, {"text": "optima auc\u2122 analytical ultracentrifuge", "rank": 0.109}, {"text": "atom probe mass spectra", "rank": 0.105}, {"text": "systematic energy deficits", "rank": 0.097}, {"text": "molecular relaxation times", "rank": 0.097}], "title_abstract_phrases": [{"text": "laser power calibration standards", "rank": 0.08}, {"text": "laser power calibration", "rank": 0.08}, {"text": "improved laser power sensor calibration accuracy", "rank": 0.079}, {"text": "laser power sensor calibration", "rank": 0.078}, {"text": "calibration accuracy", "rank": 0.069}]}