{"cluster": 72, "subcluster": 2, "abstract_phrases": [{"text": "dental practice", "rank": 0.06}, {"text": "covid-19 infection", "rank": 0.06}, {"text": "oral care practice", "rank": 0.059}, {"text": "proper hand hygiene practices", "rank": 0.058}, {"text": "dental students", "rank": 0.058}], "title_phrases": [{"text": "covid-19 outbreak", "rank": 0.087}, {"text": "covid-19 patientsepidemiological aspects", "rank": 0.079}, {"text": "medical laboratory science students", "rank": 0.076}, {"text": "final year medical students", "rank": 0.076}, {"text": "orotta national referral hospital", "rank": 0.076}], "title_abstract_phrases": [{"text": "covid-19 infection", "rank": 0.06}, {"text": "dental practice", "rank": 0.06}, {"text": "oral care practice", "rank": 0.059}, {"text": "proper hand hygiene practices", "rank": 0.058}, {"text": "dental students", "rank": 0.058}]}