{"cluster": 73, "subcluster": 19, "abstract_phrases": [{"text": "covid-19 pandemic", "rank": 0.07}, {"text": "covid-19 infection", "rank": 0.067}, {"text": "covid-19", "rank": 0.066}, {"text": "pregnant women", "rank": 0.063}, {"text": "italian pregnant women", "rank": 0.061}], "title_phrases": [{"text": "covid-19 epidemic declaration", "rank": 0.148}, {"text": "covid-19 pandemicthe impact", "rank": 0.145}, {"text": "covid-19 outbreak", "rank": 0.139}, {"text": "covid-19", "rank": 0.135}, {"text": "perceived mental healthcare", "rank": 0.113}], "title_abstract_phrases": [{"text": "covid-19", "rank": 0.073}, {"text": "covid-19 outbreak", "rank": 0.073}, {"text": "covid-19 infection", "rank": 0.072}, {"text": "covid-19 epidemic declaration", "rank": 0.069}, {"text": "covid-19 pandemicnovel corona virus disease", "rank": 0.068}]}